wikmd/__init__.py
wikmd/cache.py
wikmd/config.py
wikmd/git_manager.py
wikmd/image_manager.py
wikmd/knowledge_graph.py
wikmd/search.py
wikmd/utils.py
wikmd/web_dependencies.py
wikmd/wiki.py
wikmd/wikmd-config.yaml
wikmd/plugins/__init__.py
wikmd/plugins/load_plugins.py
wikmd/plugins/alerts/__init__.py
wikmd/plugins/alerts/alerts.py
wikmd/plugins/draw/__init__.py
wikmd/plugins/draw/default_draw
wikmd/plugins/draw/draw.py
wikmd/plugins/embed-pages/__init__.py
wikmd/plugins/embed-pages/embed-pages.py
wikmd/plugins/mermaid/__init__.py
wikmd/plugins/mermaid/mermaid.py
wikmd/plugins/plantuml/__init__.py
wikmd/plugins/plantuml/plantuml.py
wikmd/plugins/swagger/__init__.py
wikmd/plugins/swagger/swagger.py
wikmd/static/favicon.ico
wikmd/static/css/codemirror.custom.css
wikmd/static/css/codemirror.custom.dark.css
wikmd/static/css/filepond.dark.css
wikmd/static/css/swagger-ui.css
wikmd/static/css/wiki.colors.css
wikmd/static/css/wiki.css
wikmd/static/css/wiki.dark.css
wikmd/static/images/contrast-2-fill.svg
wikmd/static/images/file-copy-white.svg
wikmd/static/images/file-copy.svg
wikmd/static/images/graph_5.svg
wikmd/static/images/knowledge-graph.png
wikmd/static/images/readme-img.png
wikmd/static/images/wiki.gif
wikmd/static/images/wiki.png
wikmd/static/images/wiki2.gif
wikmd/static/js/copypaste.js
wikmd/static/js/drawio.js
wikmd/static/js/swagger-ui-bundle.js
wikmd/templates/base.html
wikmd/templates/content.html
wikmd/templates/index.html
wikmd/templates/knowledge-graph.html
wikmd/templates/list_files.html
wikmd/templates/login.html
wikmd/templates/new.html
wikmd/templates/search.html
wikmd/wiki_template/Features.md
wikmd/wiki_template/How to use the wiki.md
wikmd/wiki_template/Markdown cheatsheet.md
wikmd/wiki_template/Using the version control system.md
wikmd/wiki_template/homepage.md
wikmd-1.10.6.dist-info/LICENSE
wikmd-1.10.6.dist-info/METADATA
wikmd-1.10.6.dist-info/WHEEL
wikmd-1.10.6.dist-info/entry_points.txt
wikmd-1.10.6.dist-info/top_level.txt
wikmd-1.10.6.dist-info/RECORD
