Metadata-Version: 2.1
Name: wikmd
Version: 1.10.6
Summary: A file-based wiki that aims for simplicity.
Author: linbreux
Requires-Python: >=3.8
License-File: LICENSE
Requires-Dist: Flask ==3.0.2
Requires-Dist: GitPython ==3.1.42
Requires-Dist: Markdown ==3.5.2
Requires-Dist: PyYAML ==6.0.1
Requires-Dist: Werkzeug ==3.0.3
Requires-Dist: Whoosh ==2.7.4
Requires-Dist: beautifulsoup4 ==4.12.3
Requires-Dist: pandoc-eqnos ==2.5.0
Requires-Dist: pandoc-fignos ==2.4.0
Requires-Dist: pandoc-secnos ==2.2.2
Requires-Dist: pandoc-tablenos ==2.3.0
Requires-Dist: pandoc-xnos ==2.5.0
Requires-Dist: pandocfilters ==1.5.1
Requires-Dist: pypandoc-binary ==1.13
Requires-Dist: pypandoc ==1.13
Requires-Dist: requests ==2.32.2
Requires-Dist: lxml ==5.1.0
Requires-Dist: watchdog ==2.1.9
Requires-Dist: cachelib ==0.12.0
Provides-Extra: dev
Requires-Dist: pytest ; extra == 'dev'
